MANIFEST.in
README.md
requirements.txt
setup.cfg
setup.py
gatheros/__init__.py
gatheros/gatheros.py
gatheros/gatheros_edit.py
gatheros/gatheros_exec.py
gatheros/gatheros_show.py
gatheros.egg-info/PKG-INFO
gatheros.egg-info/SOURCES.txt
gatheros.egg-info/dependency_links.txt
gatheros.egg-info/entry_points.txt
gatheros.egg-info/requires.txt
gatheros.egg-info/top_level.txt
gatheros/commands/LinuxEnum.json
gatheros/editor/__init__.py
gatheros/editor/cmd_interface.py
gatheros/editor/populator.py
gatheros/editor/struct_manager.py
gatheros/execute/__init__.py
gatheros/execute/command_function.py
gatheros/execute/execution_unit.py
gatheros/show/__init__.py
gatheros/show/application.py
gatheros/show/static/bootstrap.min.css
gatheros/show/static/bootstrap.min.js
gatheros/show/static/linux_logo.png
gatheros/show/static/windows_logo.png
gatheros/show/templates/commands.html
gatheros/show/templates/index.html