Metadata-Version: 1.1
Name: gatheros
Version: 0.1.0
Summary: A suite for gathering and presenting OS related information
Home-page: https://github.com/operatorequals/gatheros
Author: John Torakis
Author-email: john.torakis@gmail.com
License: BSD
Download-URL: https://github.com/operatorequals/gatheros/tarball/0.1.0
Platform: UNKNOWN
Classifier: Development Status :: 3 - Alpha
Classifier: Intended Audience :: Developers
Classifier: Programming Language :: Python :: 2
Classifier: Operating System :: POSIX :: Linux
